LICENSE
README.rst
setup.cfg
setup.py
sqlalchemy_vertica/__init__.py
sqlalchemy_vertica/base.py
sqlalchemy_vertica/dialect_pyodbc.py
sqlalchemy_vertica/dialect_vertica_python.py
sqlalchemy_vertica/requirements.py
sqlalchemy_vertica_dialec.egg-info/PKG-INFO
sqlalchemy_vertica_dialec.egg-info/SOURCES.txt
sqlalchemy_vertica_dialec.egg-info/dependency_links.txt
sqlalchemy_vertica_dialec.egg-info/entry_points.txt
sqlalchemy_vertica_dialec.egg-info/requires.txt
sqlalchemy_vertica_dialec.egg-info/top_level.txt
test/test_sqlalchemy_vertica_dialect.py
test/test_suite.py