Metadata-Version: 2.1
Name: sqlalchemy-vertica-dialec
Version: 0.1.3
Summary: Vertica dialect for sqlalchemy
Home-page: https://github.com/vishalkSimplify/sqlalchemy-vertica-dialect.git
Author: Narendra Prabhu
License: MIT
Download-URL: https://github.com/vishalkSimplify/sqlalchemy-vertica-dialect.git/tarball/0.1.3
Platform: UNKNOWN
Provides-Extra: pyodbc
Provides-Extra: vertica-python
License-File: LICENSE
